dffml_config_image/__init__.py
dffml_config_image/configloader.py
dffml_config_image/version.py
tests/__init__.py
tests/test_config.py
dffml_config_image-0.1.0.post0.dist-info/LICENSE
dffml_config_image-0.1.0.post0.dist-info/METADATA
dffml_config_image-0.1.0.post0.dist-info/WHEEL
dffml_config_image-0.1.0.post0.dist-info/entry_points.txt
dffml_config_image-0.1.0.post0.dist-info/top_level.txt
dffml_config_image-0.1.0.post0.dist-info/RECORD
